Workbook

Sheet Inputs
A1: Bluebird SaaS — Driver Inputs
B3: 2026 | C3: 2027 | D3: 2028 | E3: 2029
A4: Revenue | B4: 10000000
A5: Revenue growth % | C5: 0.4 | D5: 0.35 | E5: 0.3
A6: COGS % of revenue | B6: 0.3 | C6: 0.3 | D6: 0.3 | E6: 0.3
A7: OpEx % of revenue | B7: 0.6 | C7: 0.55 | D7: 0.5 | E7: 0.45
A9: D&A ($) | B9: 1000000
A10: CapEx ($) | B10: 2000000
A11: Interest rate on debt | B11: 0.06
A12: Tax rate | B12: 0.25
A13: Opening debt | B13: 10000000
A14: Common stock | B14: 8000000
A15: DSO (days) | B15: 30
A16: DPO (days) | B16: 45
A17: Opening cash (end 2026) | B17: 15000000
A18: Opening PP&E (end 2026) | B18: 5000000

Sheet Income Statement
A1: Income Statement
B3: 2026 | C3: 2027 | D3: 2028 | E3: 2029
A4: Revenue | B4: =Inputs!B4 -> 10000000 | C4: =B4*(1+Inputs!C5) -> 14000000 | D4: =C4*(1+Inputs!D5) -> 18900000 | E4: =D4*(1+Inputs!E5) -> 24570000
A5: COGS | B5: =B4*Inputs!B6 -> 3000000 | C5: =C4*Inputs!C6 -> 4200000 | D5: =D4*Inputs!D6 -> 5670000 | E5: =E4*Inputs!E6 -> 7371000
A6: Gross profit | B6: =B4-B5 -> 7000000 | C6: =C4-C5 -> 9800000 | D6: =D4-D5 -> 13230000 | E6: =E4-E5 -> 17199000
A7: OpEx | B7: =B4*Inputs!B7 -> 6000000 | C7: =C4*Inputs!C7 -> 7700000 | D7: =D4*Inputs!D7 -> 9450000 | E7: =E4*Inputs!E7 -> 11056500
A8: EBITDA | B8: =B6-B7 -> 1000000 | C8: =C6-C7 -> 2100000 | D8: =D6-D7 -> 3780000 | E8: =E6-E7 -> 6142500
A9: D&A | B9: =Inputs!B9 -> 1000000 | C9: =Inputs!B9 -> 1000000 | D9: =Inputs!B9 -> 1000000 | E9: =Inputs!B9 -> 1000000
A10: EBIT | B10: =B8-B9 -> 0 | C10: =C8-C9 -> 1100000 | D10: =D8-D9 -> 2780000 | E10: =E8-E9 -> 5142500
A11: Interest expense | B11: =Inputs!B11*Inputs!B13 -> 600000 | C11: =Inputs!B11*Inputs!B13 -> 600000 | D11: =Inputs!B11*Inputs!B13 -> 600000 | E11: =Inputs!B11*Inputs!B13 -> 600000
A12: Pre-tax income | B12: =B10-B11 -> -600000 | C12: =C10-C11 -> 500000 | D12: =D10-D11 -> 2180000 | E12: =E10-E11 -> 4542500
A13: Tax | B13: =Inputs!B12*MAX(0,B12) -> 0 | C13: =Inputs!B12*MAX(0,C12) -> 125000 | D13: =Inputs!B12*MAX(0,D12) -> 545000 | E13: =Inputs!B12*MAX(0,E12) -> 1135625
A14: Net income | B14: =B12-B13 -> -600000 | C14: =C12-C13 -> 375000 | D14: =D12-D13 -> 1635000 | E14: =E12-E13 -> 3406875

Sheet Balance Sheet
A1: Balance Sheet
B3: 2026 | C3: 2027 | D3: 2028 | E3: 2029
A4: Cash | B4: =Inputs!B17 -> 15000000 | C4: =B4+'Cash Flow'!C11 -> 14194178 | D4: =C4+'Cash Flow'!D11 -> 14607671 | E4: =D4+'Cash Flow'!E11 -> 16758231
A5: A/R | B5: ='Income Statement'!B4*Inputs!B15/365 -> 821917.81 | C5: ='Income Statement'!C4*Inputs!B15/365 -> 1150684.9 | D5: ='Income Statement'!D4*Inputs!B15/365 -> 1553424.7 | E5: ='Income Statement'!E4*Inputs!B15/365 -> 2019452.1
A6: PP&E (net) | B6: =Inputs!B18 -> 5000000 | C6: =B6+Inputs!B10-'Income Statement'!C9 -> 6000000 | D6: =C6+Inputs!B10-'Income Statement'!D9 -> 7000000 | E6: =D6+Inputs!B10-'Income Statement'!E9 -> 8000000
A7: Total assets | B7: =SUM(B4:B6) -> 20821918 | C7: =SUM(C4:C6) -> 21344863 | D7: =SUM(D4:D6) -> 23161096 | E7: =SUM(E4:E6) -> 26777683
A9: A/P | B9: ='Income Statement'!B5*Inputs!B16/365 -> 369863.01 | C9: ='Income Statement'!C5*Inputs!B16/365 -> 517808.22 | D9: ='Income Statement'!D5*Inputs!B16/365 -> 699041.1 | E9: ='Income Statement'!E5*Inputs!B16/365 -> 908753.42
A10: Debt | B10: =Inputs!B13 -> 10000000 | C10: =Inputs!B13 -> 10000000 | D10: =Inputs!B13 -> 10000000 | E10: =Inputs!B13 -> 10000000
A11: Common stock | B11: =Inputs!B14 -> 8000000 | C11: =Inputs!B14 -> 8000000 | D11: =Inputs!B14 -> 8000000 | E11: =Inputs!B14 -> 8000000
A12: Retained earnings | B12: =(B4+B5+B6)-(B9+B10+B11) -> 2452054.8 | C12: =B12+'Income Statement'!C14 -> 2827054.8 | D12: =C12+'Income Statement'!D14 -> 4462054.8 | E12: =D12+'Income Statement'!E14 -> 7868929.8
A13: Total L+E | B13: =B9+SUM(B10:B12) -> 20821918 | C13: =C9+SUM(C10:C12) -> 21344863 | D13: =D9+SUM(D10:D12) -> 23161096 | E13: =E9+SUM(E10:E12) -> 26777683

Sheet Cash Flow
A1: Cash Flow
B3: 2026 | C3: 2027 | D3: 2028 | E3: 2029
A4: Net income | B4: ='Income Statement'!B14 -> -600000 | C4: ='Income Statement'!C14 -> 375000 | D4: ='Income Statement'!D14 -> 1635000 | E4: ='Income Statement'!E14 -> 3406875
A5: + D&A | B5: ='Income Statement'!B9 -> 1000000 | C5: ='Income Statement'!C9 -> 1000000 | D5: ='Income Statement'!D9 -> 1000000 | E5: ='Income Statement'!E9 -> 1000000
A6: − ΔA/R | B6: 0 | C6: =-('Balance Sheet'!C5-'Balance Sheet'!B5) -> -328767.12 | D6: =-('Balance Sheet'!D5-'Balance Sheet'!C5) -> -402739.73 | E6: =-('Balance Sheet'!E5-'Balance Sheet'!D5) -> -466027.4
A7: + ΔA/P | B7: 0 | C7: ='Balance Sheet'!C9-'Balance Sheet'!B9 -> 147945.21 | D7: ='Balance Sheet'!D9-'Balance Sheet'!C9 -> 181232.88 | E7: ='Balance Sheet'!E9-'Balance Sheet'!D9 -> 209712.33
A8: CF from operations | B8: =SUM(B4:B7) -> 400000 | C8: =SUM(C4:C7) -> 1194178.1 | D8: =SUM(D4:D7) -> 2413493.2 | E8: =SUM(E4:E7) -> 4150559.9
A9: CF from investing | B9: 0 | C9: =-Inputs!B10 -> -2000000 | D9: =-Inputs!B10 -> -2000000 | E9: =-Inputs!B10 -> -2000000
A10: CF from financing | B10: 0 | C10: 0 | D10: 0 | E10: 0
A11: Net change in cash | B11: =B8+B9+B10 -> 400000 | C11: =C8+C9+C10 -> -805821.92 | D11: =D8+D9+D10 -> 413493.15 | E11: =E8+E9+E10 -> 2150559.9
A12: Beginning cash | B12: 0 | C12: =B13 -> 15000000 | D12: =C13 -> 14194178 | E12: =D13 -> 14607671
A13: Ending cash | B13: =Inputs!B17 -> 15000000 | C13: =C12+C11 -> 14194178 | D13: =D12+D11 -> 14607671 | E13: =E12+E11 -> 16758231
