Workbook

Sheet Cap Table
A1: Holder | B1: Class | C1: Shares | D1: % FD
A2: Founder A | B2: Common | C2: 4000000 | D2: =C2/$C$8 -> 0.38095238
A3: Founder B | B3: Common | C3: 3000000 | D3: =C3/$C$8 -> 0.28571429
A4: Seed Investor 1 | B4: Preferred Seed | C4: 1500000 | D4: =C4/$C$8 -> 0.14285714
A5: Seed Investor 2 | B5: Preferred Seed | C5: 1000000 | D5: =C5/$C$8 -> 0.095238095
A6: Option Pool (granted) | B6: Options (granted) | C6: 500000 | D6: =C6/$C$8 -> 0.047619048
A7: Option Pool (unallocated) | B7: Options (unallocated) | C7: 500000 | D7: =C7/$C$8 -> 0.047619048
A8: Total FD | C8: =SUM(C2:C7) -> 10500000 | D8: =SUM(D2:D7) -> 1

Sheet SAFE Convert
A1: SAFE Conversion
B3: Harbor Fund | C3: Archer Angels
A4: Investment | B4: 2000000 | C4: 1500000
A5: Valuation cap | B5: 20000000 | C5: 25000000
A6: Discount | B6: 0 | C6: 0.2
A7: Pre-round FD (from Cap Table) | B7: ='Cap Table'!C8 -> 10500000 | C7: ='Cap Table'!C8 -> 10500000
A8: Headline price (from Series A) | B8: ='Series A'!B5 -> 3.8095238 | C8: ='Series A'!B5 -> 3.8095238
A9: Cap price | B9: =B5/B7 -> 1.9047619 | C9: =C5/C7 -> 2.3809524
A10: Discount price | B10: =(1-B6)*B8 -> 3.8095238 | C10: =(1-C6)*C8 -> 3.047619
A11: Conversion price | B11: =MIN(B9,B10) -> 1.9047619 | C11: =MIN(C9,C10) -> 2.3809524
A12: Shares issued | B12: =B4/B11 -> 1050000 | C12: =C4/C11 -> 630000
A14: Total SAFE shares | B14: =B12+C12 -> 1680000

Sheet Series A
A1: Series A — round mechanics
A3: Pre-money valuation | B3: 40000000
A4: Pre-round FD (from Cap Table) | B4: ='Cap Table'!C8 -> 10500000
A5: Headline price per share | B5: =B3/B4 -> 3.8095238
A6: Round size (new money) | B6: 15000000
A7: Option pool target (post-money) | B7: 0.1
A8: Pre-round unallocated pool | B8: 500000
A11: SAFE shares (from SAFE Convert) | B11: ='SAFE Convert'!B14 -> 1680000
A12: New investor shares | B12: =B6/B5 -> 3937500
A13: Option pool top-up | B13: =(B7*(B4+B11+B12)-B8)/(1-B7) -> 1235277.8
A14: Post-money fully diluted shares | B14: =B4+B11+B12+B13 -> 17352778
