Workbook

Sheet __temp__

Sheet Detailed Cap Table
H2: Current
B3: Shareholder | C3: Founders CS | D3: RSA | E3: Options | F3: Exercised Options | G3: Total | H3: % FDS
B4: Brian Hazzard | C4: 3600000 | G4: =SUM(C4:F4) -> 3600000 | H4: =G4/$G$23 -> 0.36959988
B5: David Wolpoff | C5: 3600000 | G5: =SUM(C5:F5) -> 3600000 | H5: =G5/$G$23 -> 0.36959988
B6: Ian Lee | C6: 222187 | G6: =SUM(C6:F6) -> 222187 | H6: =G6/$G$23 -> 0.022811191
B7: Kyle Haugsness | C7: 592500 | G7: =SUM(C7:F7) -> 592500 | H7: =G7/$G$23 -> 0.06082998
B8: Paul Riegle | C8: 592500 | G8: =SUM(C8:F8) -> 592500 | H8: =G8/$G$23 -> 0.06082998
B9: Chris Butts | C9: 13500 | D9: 98900 | G9: =SUM(C9:F9) -> 112400 | H9: =G9/$G$23 -> 0.011539729
B10: Maurice Granfield | C10: 9000 | G10: =SUM(C10:F10) -> 9000 | H10: =G10/$G$23 -> 0.00092399969
B11: Pawan Lakshmanan | D11: 95000 | G11: =SUM(C11:F11) -> 95000 | H11: =G11/$G$23 -> 0.0097533301
B12: Matthew Howe | E12: 25000 | G12: =SUM(C12:F12) -> 25000 | H12: =G12/$G$23 -> 0.0025666658
B13: Andrew Ethan Boyce-Lewis | E13: 41562 | G13: =SUM(C13:F13) -> 41562 | H13: =G13/$G$23 -> 0.0042670306
B14: Eric McIntyre | D14: 285000 | G14: =SUM(C14:F14) -> 285000 | H14: =G14/$G$23 -> 0.02925999
B15: Patrick Heath | D15: 50000 | G15: =SUM(C15:F15) -> 50000 | H15: =G15/$G$23 -> 0.0051333316
B16: Chris Lord | D16: 285000 | G16: =SUM(C16:F16) -> 285000 | H16: =G16/$G$23 -> 0.02925999
B17: Eric Freedman | E17: 96186 | G17: =SUM(C17:F17) -> 96186 | H17: =G17/$G$23 -> 0.0098750927
B18: Miguel Bollar | E18: 48095 | G18: =SUM(C18:F18) -> 48095 | H18: =G18/$G$23 -> 0.0049377517
B19: Bradly Matheson | F19: 12395 | G19: =SUM(C19:F19) -> 12395 | H19: =G19/$G$23 -> 0.0012725529
B20: Cole Proctor | F20: 8333 | G20: =SUM(C20:F20) -> 8333 | H20: =G20/$G$23 -> 0.00085552105
B21: Available Options | D21: 65105 | G21: =SUM(C21:F21) -> 65105 | H21: =G21/$G$23 -> 0.0066841111
B23: Total | C23: =SUM(C4:C21) -> 8629687 | D23: =SUM(D4:D21) -> 879005 | E23: =SUM(E4:E21) -> 210843 | F23: =SUM(F4:F21) -> 20728 | G23: =SUM(G4:G21) -> 9740263

Sheet SAFE Investments
B3: Shareholder | C3: SAFE | E3: Notes
B4: Chris Butts | C4: 25000 | E4: IRA is actual investor
B5: Maurice Granfield | C5: 25000
B6: Accomplice Founder Fund, L.P. | C6: 137170.75
B7: Accomplice Fund IV, L.P | C7: 3846829.2
B8: Amir Bagherzadeh | C8: 16566 | E8: Transfer from Owl Rocl Capital II, LLC (Accomplice)
B9: Elizabeth A. Donaghey Irrevocable Trust 2016 | C9: 250000
B10: Gunderson Partners | C10: 100000
B11: Joe Arcadi | C11: 300000 | E11: IRA is actual investor
B12: Kamal Ravikant Capital, LP - E4 | C12: 37500 | E12: Navel
B13: Maria Cirino | C13: 250000
B14: Mike Viscuso | C14: 100000
B15: Mozart Holdings, LLC | C15: 41164 | E15: Transfer from Owl Rocl Capital II, LLC (Accomplice)
B16: Orcinus Generational Irrevocable Trust - 2024 | C16: 2328778 | E16: Transfer from Owl Rocl Capital II, LLC (Accomplice)
B17: Owl Rock Capital III, LLC | C17: 1506000 | E17: Accomplice
B18: Ralph Folz | C18: 50000
B19: Ravikant Capital, LP - F3 | C19: 212500 | E19: Navel
B20: Sean Leach | C20: 25000
B21: The Francis V. Castellucci Trust - 2020 | C21: 61746 | E21: Transfer from Owl Rocl Capital II, LLC (Accomplice)
B22: The Patrick M. Morley 1999 Trust, | C22: 100000
B23: Tom Barsi | C23: 100000
B24: Travis MacInnes | C24: 61746 | E24: Transfer from Owl Rocl Capital II, LLC (Accomplice)
B25: UWS West End Family Trust | C25: 250000 | E25: Mark Lotke
B27: Total | C27: =SUM(C4:C25) -> 9825000

Sheet PreA
B4: THINK MORE SECURITY & 1011 VENTURES PRE-SERIES A
B5: PRE-SERIES A CAPITALIZATION
C6: Common | D6: SAFE | F6: Total Capitalization
C7: # of | D7: $ | F7: Total FD | G7: %
C8: Shares | D8: Invested | F8: Shares | G8: FD
B9: Common Stock and Options:
B10: Brian Hazzard | C10: ='Detailed Cap Table'!C4 -> 3600000 | F10: =C10 -> 3600000 | G10: =F10/$F$21 -> 0.36959988
B11: David Wolpoff | C11: ='Detailed Cap Table'!C5 -> 3600000 | F11: =C11 -> 3600000 | G11: =F11/$F$21 -> 0.36959988
B12: Other Common Shareholders | C12: ='Detailed Cap Table'!C6+'Detailed Cap Table'!C7+'Detailed Cap Table'!C8+'Detailed Cap Table'!C9+'Detailed Cap Table'!C10+'Detailed Cap Table'!F19+'Detailed Cap Table'!F20 -> 1450415 | F12: =C12 -> 1450415 | G12: =F12/$F$21 -> 0.14890922
B13: ESOP Outstanding | C13: =SUM('Detailed Cap Table'!D4:D20)+SUM('Detailed Cap Table'!E4:E20) -> 1024743 | F13: =C13 -> 1024743 | G13: =F13/$F$21 -> 0.10520691
B14: ESOP Available | C14: ='Detailed Cap Table'!D21 -> 65105 | F14: =C14 -> 65105 | G14: =F14/$F$21 -> 0.0066841111
B15: Total Common | C15: =SUM(C10:C14) -> 9740263 | F15: =SUM(F10:F14) -> 9740263 | G15: =SUM(G10:G14) -> 1
B16: SAFE Investors:
B17: Accomplice | D17: ='SAFE Investments'!C6+'SAFE Investments'!C7+'SAFE Investments'!C8+'SAFE Investments'!C15+'SAFE Investments'!C16+'SAFE Investments'!C17+'SAFE Investments'!C21+'SAFE Investments'!C24 -> 8000000 | F17: =C17 -> 0 | G17: =F17/$F$21 -> 0
B18: Other SAFE Investors | D18: ='SAFE Investments'!C27-D17 -> 1825000 | F18: =C18 -> 0 | G18: =F18/$F$21 -> 0
B21: Totals | C21: =C15 -> 9740263 | D21: =SUM(D17:D18) -> 9825000 | F21: =F15 -> 9740263 | G21: =SUM(G10:G14) -> 1
B23: Implied Price per Share | C23: =D24/C25 -> 5.1333316
B24: SAFE Post-Money Valuation Cap | D24: 50000000
B25: Company Capitalization (pre-A) | C25: =F21 -> 9740263

Sheet Series A
B1: THINK MORE SECURITY
B2: 1011 VENTURES SERIES A
C4: Common | D4: SAFE | G4: Option | I4: Series A | L4: Option | N4: Total Capitalization
C5: # of | D5: $ | E5: Preferred | G5: Pool + | I5: $ | J5: Preferred | L5: Pool + | N5: Total FD | O5: %
C6: Shares | D6: Invested | E6: SAFE Shares | G6: Pre SAFE | I6: Invested | J6: Shares | L6: Pre A | N6: Shares | O6: FD
B7: Common Stock and Options:
B8: Brian Hazzard | C8: =PreA!C10 -> 3600000 | N8: =C8+E8+G8+J8+L8 -> 3600000 | O8: =N8/$N$21 -> 0.19407533
B9: David Wolpoff | C9: =PreA!C11 -> 3600000 | N9: =C9+E9+G9+J9+L9 -> 3600000 | O9: =N9/$N$21 -> 0.19407533
B10: Other Common Shareholders | C10: =PreA!C12 -> 1450415 | N10: =C10+E10+G10+J10+L10 -> 1450415 | O10: =N10/$N$21 -> 0.078191604
B11: ESOP Outstanding | C11: =PreA!C13 -> 1024743 | N11: =C11+E11+G11+J11+L11 -> 1024743 | O11: =N11/$N$21 -> 0.055243705
B12: ESOP Available | C12: =PreA!C14 -> 65105 | L12: =ROUND((C31*(C13+E21+J21)-C12)/(1-C31),0) -> 1789845 | N12: =C12+E12+G12+J12+L12 -> 1854950 | O12: =N12/$N$21 -> 0.10000001
B13: Total Common | C13: =SUM(C8:C12) -> 9740263 | D13: =SUM(D8:D12) -> 0 | E13: =SUM(E8:E12) -> 0 | G13: =SUM(G8:G12) -> 0 | I13: =SUM(I8:I12) -> 0 | J13: =SUM(J8:J12) -> 0 | L13: =SUM(L8:L12) -> 1789845 | N13: =SUM(N8:N12) -> 11530108 | O13: =N13/$N$21 -> 0.62158599
B14: Preferred Rounds
B15: Accomplice | D15: =PreA!D17 -> 8000000 | E15: =IFERROR(ROUND(D15/$E$22,0),0) -> 1939567 | I15: 5000000 | J15: =IFERROR(ROUND(I15/$J$22,0),0) -> 1159340 | N15: =C15+E15+G15+J15+L15 -> 3098907 | O15: =N15/$N$21 -> 0.1670615
B16: Other SAFE Investors | D16: =PreA!D18 -> 1825000 | E16: =IFERROR(ROUND(D16/$E$22,0),0) -> 442464 | N16: =C16+E16+G16+J16+L16 -> 442464 | O16: =N16/$N$21 -> 0.023853152
B17: 1011 Ventures | I17: 12000000 | J17: =IFERROR(ROUND(I17/$J$22,0),0) -> 2782415 | N17: =C17+E17+G17+J17+L17 -> 2782415 | O17: =N17/$N$21 -> 0.14999948
B18: Other Series A Investors | I18: =I21-I15-I17 -> 3000000 | J18: =IFERROR(ROUND(I18/$J$22,0),0) -> 695604 | N18: =C18+E18+G18+J18+L18 -> 695604 | O18: =N18/$N$21 -> 0.037499883
B21: Totals | C21: =C13+SUM(C15:C18) -> 9740263 | D21: =D13+SUM(D15:D18) -> 9825000 | E21: =E13+SUM(E15:E18) -> 2382031 | G21: =G13+SUM(G15:G18) -> 0 | I21: 20000000 | J21: =SUM(J15:J18) -> 4637359 | L21: =L13+SUM(L15:L18) -> 1789845 | N21: =N13+SUM(N15:N18) -> 18549498 | O21: =SUM(O13,O15:O18) -> 1
B22: Price per Share | E22: =(C28-D21)/PreA!F21 -> 4.124632 | J22: =IFERROR(ROUND(J23/(C13+E21+L12),4),0) -> 4.3128
B23: Pre-Money Valuation | J23: 60000000
B24: Post-Money Valuation | J24: =J23+I21 -> 80000000
B25: % Ownership Check | E25: =E21/(E21+C13+L12) -> 0.17121961 | J25: =J21/N21 -> 0.24999916
B27: Series A Assumptions:
B28: SAFE Post-Money Valuation Cap | C28: 50000000
B29: Pre-Money Valuation | C29: =J23 -> 60000000
B30: Total Raised | C30: =I21 -> 20000000
B31: Option Pool Expansion (% of post-money FD) | C31: 0.1
B32: 1011 Ventures Investment | C32: =I17 -> 12000000
B33: Accomplice New Money | C33: =I15 -> 5000000
B34: Other Series A Investors | C34: =I18 -> 3000000

Sheet Series B
B1: THINK MORE SECURITY
B2: 1011 VENTURES SERIES B
C4: Common | D4: SAFE | G4: Option | I4: Series A | L4: Option | N4: Series B | Q4: Option | S4: Total Capitalization
C5: # of | D5: $ | E5: Preferred | G5: Pool + | I5: $ | J5: Preferred | L5: Pool + | N5: $ | O5: Preferred | Q5: Pool + | S5: Total FD | T5: %
C6: Shares | D6: Invested | E6: SAFE Shares | G6: Pre SAFE | I6: Invested | J6: Shares | L6: Pre A | N6: Invested | O6: Shares | Q6: Pre B | S6: Shares | T6: FD
B7: Common Stock and Options:
B8: Brian Hazzard | C8: ='Series A'!C8 -> 3600000 | E8: ='Series A'!E8 -> 0 | G8: ='Series A'!G8 -> 0 | J8: ='Series A'!J8 -> 0 | L8: ='Series A'!L8 -> 0 | S8: =C8+E8+G8+J8+L8+O8+Q8 -> 3600000 | T8: =S8/$S$22 -> 0.14814414
B9: David Wolpoff | C9: ='Series A'!C9 -> 3600000 | E9: ='Series A'!E9 -> 0 | G9: ='Series A'!G9 -> 0 | J9: ='Series A'!J9 -> 0 | L9: ='Series A'!L9 -> 0 | S9: =C9+E9+G9+J9+L9+O9+Q9 -> 3600000 | T9: =S9/$S$22 -> 0.14814414
B10: Other Common Shareholders | C10: ='Series A'!C10 -> 1450415 | E10: ='Series A'!E10 -> 0 | G10: ='Series A'!G10 -> 0 | J10: ='Series A'!J10 -> 0 | L10: ='Series A'!L10 -> 0 | S10: =C10+E10+G10+J10+L10+O10+Q10 -> 1450415 | T10: =S10/$S$22 -> 0.059686244
B11: ESOP Outstanding | C11: ='Series A'!C11 -> 1024743 | E11: ='Series A'!E11 -> 0 | G11: ='Series A'!G11 -> 0 | J11: ='Series A'!J11 -> 0 | L11: ='Series A'!L11 -> 0 | S11: =C11+E11+G11+J11+L11+O11+Q11 -> 1024743 | T11: =S11/$S$22 -> 0.042169352
B12: ESOP Available | C12: ='Series A'!C12 -> 65105 | E12: ='Series A'!E12 -> 0 | G12: ='Series A'!G12 -> 0 | J12: ='Series A'!J12 -> 0 | L12: ='Series A'!L12 -> 1789845 | Q12: =ROUND(C34*S22,0) -> 1701046 | S12: =C12+E12+G12+J12+L12+O12+Q12 -> 3555996 | T12: =S12/$S$22 -> 0.14633332
B13: Total Common | C13: =SUM(C8:C12) -> 9740263 | D13: =SUM(D8:D12) -> 0 | E13: =SUM(E8:E12) -> 0 | G13: =SUM(G8:G12) -> 0 | I13: =SUM(I8:I12) -> 0 | J13: =SUM(J8:J12) -> 0 | L13: =SUM(L8:L12) -> 1789845 | N13: =SUM(N8:N12) -> 0 | O13: =SUM(O8:O12) -> 0 | Q13: =SUM(Q8:Q12) -> 1701046 | S13: =SUM(S8:S12) -> 13231154 | T13: =S13/$S$22 -> 0.54447719
B14: Preferred Rounds
B15: Accomplice | C15: ='Series A'!C15 -> 0 | D15: ='Series A'!D15 -> 8000000 | E15: ='Series A'!E15 -> 1939567 | G15: ='Series A'!G15 -> 0 | I15: ='Series A'!I15 -> 5000000 | J15: ='Series A'!J15 -> 1159340 | L15: ='Series A'!L15 -> 0 | N15: =N22*(1-C33)*('Series A'!E15+'Series A'!J15)/('Series A'!E21+'Series A'!J21) -> 6622171.6 | O15: =IFERROR(ROUND(N15/$O$24,0),0) -> 894018 | S15: =C15+E15+G15+J15+L15+O15+Q15 -> 3992925 | T15: =S15/$S$22 -> 0.16431345
B16: Other SAFE Investors | C16: ='Series A'!C16 -> 0 | D16: ='Series A'!D16 -> 1825000 | E16: ='Series A'!E16 -> 442464 | G16: ='Series A'!G16 -> 0 | I16: ='Series A'!I16 -> 0 | J16: ='Series A'!J16 -> 0 | L16: ='Series A'!L16 -> 0 | N16: =N22*(1-C33)*('Series A'!E16+'Series A'!J16)/('Series A'!E21+'Series A'!J21) -> 945518.06 | O16: =IFERROR(ROUND(N16/$O$24,0),0) -> 127649 | S16: =C16+E16+G16+J16+L16+O16+Q16 -> 570113 | T16: =S16/$S$22 -> 0.023460805
B17: 1011 Ventures | C17: ='Series A'!C17 -> 0 | D17: ='Series A'!D17 -> 0 | E17: ='Series A'!E17 -> 0 | G17: ='Series A'!G17 -> 0 | I17: ='Series A'!I17 -> 12000000 | J17: ='Series A'!J17 -> 2782415 | L17: ='Series A'!L17 -> 0 | N17: =N22*(1-C33)*('Series A'!J17)/('Series A'!E21+'Series A'!J21) -> 5945847.9 | O17: =IFERROR(ROUND(N17/$O$24,0),0) -> 802712 | S17: =C17+E17+G17+J17+L17+O17+Q17 -> 3585127 | T17: =S17/$S$22 -> 0.1475321
B18: Other Series A Investors | C18: ='Series A'!C18 -> 0 | D18: ='Series A'!D18 -> 0 | E18: ='Series A'!E18 -> 0 | G18: ='Series A'!G18 -> 0 | I18: ='Series A'!I18 -> 3000000 | J18: ='Series A'!J18 -> 695604 | L18: ='Series A'!L18 -> 0 | N18: =N22*(1-C33)*('Series A'!J18)/('Series A'!E21+'Series A'!J21) -> 1486462.5 | O18: =IFERROR(ROUND(N18/$O$24,0),0) -> 200678 | S18: =C18+E18+G18+J18+L18+O18+Q18 -> 896282 | T18: =S18/$S$22 -> 0.036883034
B19: Other Series B Investors | N19: =N22*C33 -> 15000000 | O19: =IFERROR(ROUND(N19/$O$24,0),0) -> 2025057 | S19: =C19+E19+G19+J19+L19+O19+Q19 -> 2025057 | T19: =S19/$S$22 -> 0.083333422
B22: Totals | C22: =C13+SUM(C15:C19) -> 9740263 | D22: =D13+SUM(D15:D19) -> 9825000 | E22: =E13+SUM(E15:E19) -> 2382031 | G22: =G13+SUM(G15:G19) -> 0 | I22: =I13+SUM(I15:I19) -> 20000000 | J22: =J13+SUM(J15:J19) -> 4637359 | L22: =L13+SUM(L15:L19) -> 1789845 | N22: =C31 -> 30000000 | O22: =O13+SUM(O15:O19) -> 4050114 | Q22: =Q13+SUM(Q15:Q19) -> 1701046 | S22: =S13+SUM(S15:S19) -> 24300658 | T22: =T13+SUM(T15:T19) -> 1
B24: Price per Share | J24: ='Series A'!J22 -> 4.3128 | O24: =IFERROR(ROUND(O25/(S22-O22),4),0) -> 7.4072
B25: Pre-Money Valuation | J25: ='Series A'!J23 -> 60000000 | O25: 150000000
B26: Post-Money Valuation | J26: ='Series A'!J24 -> 80000000 | O26: =O25+N22 -> 180000000
B28: Series B Assumptions:
B30: Pre-Money Valuation Step-up | C30: =O25/'Series A'!J24-1 -> 0.875
B31: Total Raised | C31: 30000000
B32: % Ownership | C32: =N22/O26 -> 0.16666667
B33: % New Money | C33: 0.5
B34: Option Pool (gross % of post-B FD) | C34: 0.07
