Workbook

Sheet __temp__

Sheet Detailed Cap Table
H2: Current
B3: Shareholder | C3: Founders CS | D3: RSA | E3: Options | F3: Exercised Options | G3: Total | H3: % FDS
B4: Brian Hazzard | C4: 3600000 | G4: =SUM(C4:F4) -> 3600000 | H4: =G4/$G$23 -> 0.36959988
B5: David Wolpoff | C5: 3600000 | G5: =SUM(C5:F5) -> 3600000 | H5: =G5/$G$23 -> 0.36959988
B6: Ian Lee | C6: 222187 | G6: =SUM(C6:F6) -> 222187 | H6: =G6/$G$23 -> 0.022811191
B7: Kyle Haugsness | C7: 592500 | G7: =SUM(C7:F7) -> 592500 | H7: =G7/$G$23 -> 0.06082998
B8: Paul Riegle | C8: 592500 | G8: =SUM(C8:F8) -> 592500 | H8: =G8/$G$23 -> 0.06082998
B9: Chris Butts | C9: 13500 | D9: 98900 | G9: =SUM(C9:F9) -> 112400 | H9: =G9/$G$23 -> 0.011539729
B10: Maurice Granfield | C10: 9000 | G10: =SUM(C10:F10) -> 9000 | H10: =G10/$G$23 -> 0.00092399969
B11: Pawan Lakshmanan | D11: 95000 | G11: =SUM(C11:F11) -> 95000 | H11: =G11/$G$23 -> 0.0097533301
B12: Matthew Howe | E12: 25000 | G12: =SUM(C12:F12) -> 25000 | H12: =G12/$G$23 -> 0.0025666658
B13: Andrew Ethan Boyce-Lewis | E13: 41562 | G13: =SUM(C13:F13) -> 41562 | H13: =G13/$G$23 -> 0.0042670306
B14: Eric McIntyre | D14: 285000 | G14: =SUM(C14:F14) -> 285000 | H14: =G14/$G$23 -> 0.02925999
B15: Patrick Heath | D15: 50000 | G15: =SUM(C15:F15) -> 50000 | H15: =G15/$G$23 -> 0.0051333316
B16: Chris Lord | D16: 285000 | G16: =SUM(C16:F16) -> 285000 | H16: =G16/$G$23 -> 0.02925999
B17: Eric Freedman | E17: 96186 | G17: =SUM(C17:F17) -> 96186 | H17: =G17/$G$23 -> 0.0098750927
B18: Miguel Bollar | E18: 48095 | G18: =SUM(C18:F18) -> 48095 | H18: =G18/$G$23 -> 0.0049377517
B19: Bradly Matheson | F19: 12395 | G19: =SUM(C19:F19) -> 12395 | H19: =G19/$G$23 -> 0.0012725529
B20: Cole Proctor | F20: 8333 | G20: =SUM(C20:F20) -> 8333 | H20: =G20/$G$23 -> 0.00085552105
B21: Available Options | D21: 65105 | G21: =SUM(C21:F21) -> 65105 | H21: =G21/$G$23 -> 0.0066841111
B23: Total | C23: =SUM(C4:C21) -> 8629687 | D23: =SUM(D4:D21) -> 879005 | E23: =SUM(E4:E21) -> 210843 | F23: =SUM(F4:F21) -> 20728 | G23: =SUM(G4:G21) -> 9740263

Sheet SAFE Investments
B3: Shareholder | C3: SAFE | E3: Notes
B4: Chris Butts | C4: 25000 | E4: IRA is actual investor
B5: Maurice Granfield | C5: 25000
B6: Accomplice Founder Fund, L.P. | C6: 137170.75
B7: Accomplice Fund IV, L.P | C7: 3846829.2
B8: Amir Bagherzadeh | C8: 16566 | E8: Transfer from Owl Rocl Capital II, LLC (Accomplice)
B9: Elizabeth A. Donaghey Irrevocable Trust 2016 | C9: 250000
B10: Gunderson Partners | C10: 100000
B11: Joe Arcadi | C11: 300000 | E11: IRA is actual investor
B12: Kamal Ravikant Capital, LP - E4 | C12: 37500 | E12: Navel
B13: Maria Cirino | C13: 250000
B14: Mike Viscuso | C14: 100000
B15: Mozart Holdings, LLC | C15: 41164 | E15: Transfer from Owl Rocl Capital II, LLC (Accomplice)
B16: Orcinus Generational Irrevocable Trust - 2024 | C16: 2328778 | E16: Transfer from Owl Rocl Capital II, LLC (Accomplice)
B17: Owl Rock Capital III, LLC | C17: 1506000 | E17: Accomplice
B18: Ralph Folz | C18: 50000
B19: Ravikant Capital, LP - F3 | C19: 212500 | E19: Navel
B20: Sean Leach | C20: 25000
B21: The Francis V. Castellucci Trust - 2020 | C21: 61746 | E21: Transfer from Owl Rocl Capital II, LLC (Accomplice)
B22: The Patrick M. Morley 1999 Trust, | C22: 100000
B23: Tom Barsi | C23: 100000
B24: Travis MacInnes | C24: 61746 | E24: Transfer from Owl Rocl Capital II, LLC (Accomplice)
B25: UWS West End Family Trust | C25: 250000 | E25: Mark Lotke
B27: Total | C27: =SUM(C4:C25) -> 9825000

Sheet Series Seed
B4: SIDEKICK (THINK MORE SECURITY, INC.)
C6: Common | G6: SAFE | J6: Option | L6: Total Capitalization | N6: SAFE
C7: # of | D7: $ | E7: Preferred | G7: $ | H7: Preferred | J7: Pool + | L7: Total FD | M7: % | N7: Val Cap
C8: Shares | D8: Invested | E8: Shares | G8: Invested | H8: Shares | J8: Pre-Funding | L8: Shares | M8: FD | N8: ($)
B9: Common Stock and Options:
B10: Brian Hazzard | C10: ='Detailed Cap Table'!C4 -> 3600000 | L10: =C10+E10+H10+J10 -> 3600000 | M10: =L10/$L$21 -> 0.36959988 | N10: 50000000
B11: David Wolpoff | C11: ='Detailed Cap Table'!C5 -> 3600000 | L11: =C11+E11+H11+J11 -> 3600000 | M11: =L11/$L$21 -> 0.36959988
B12: Other Common Shareholders | C12: =SUM('Detailed Cap Table'!C6:'Detailed Cap Table'!C10) -> 1429687 | L12: =C12+E12+H12+J12 -> 1429687 | M12: =L12/$L$21 -> 0.14678115
B13: ESOP Issued & Outstanding | C13: ='Detailed Cap Table'!D9+'Detailed Cap Table'!D11+'Detailed Cap Table'!D14+'Detailed Cap Table'!D15+'Detailed Cap Table'!D16+'Detailed Cap Table'!E12+'Detailed Cap Table'!E13+'Detailed Cap Table'!E17+'Detailed Cap Table'!E18+'Detailed Cap Table'!F19+'Detailed Cap Table'!F20 -> 1045471 | L13: =C13+E13+H13+J13 -> 1045471 | M13: =L13/$L$21 -> 0.10733499
B14: ESOP Available | C14: ='Detailed Cap Table'!D21 -> 65105 | L14: =C14+E14+H14+J14 -> 65105 | M14: =L14/$L$21 -> 0.0066841111
B15: Total Common | C15: =SUM(C10:C14) -> 9740263 | D15: =SUM(D10:D14) -> 0 | E15: =SUM(E10:E14) -> 0 | G15: =SUM(G10:G14) -> 0 | H15: =SUM(H10:H14) -> 0 | J15: =SUM(J10:J14) -> 0 | L15: =SUM(L10:L14) -> 9740263 | M15: =L15/$L$21 -> 1
B16: SAFE Rounds
B17: Accomplice | G17: ='SAFE Investments'!C6+'SAFE Investments'!C7+'SAFE Investments'!C8+'SAFE Investments'!C15+'SAFE Investments'!C16+'SAFE Investments'!C17+'SAFE Investments'!C21+'SAFE Investments'!C24 -> 8000000 | L17: =C17+E17+H17+J17 -> 0 | M17: =L17/$L$21 -> 0
B18: Other SAFE Investors | G18: ='SAFE Investments'!C27-G17 -> 1825000 | L18: =C18+E18+H18+J18 -> 0 | M18: =L18/$L$21 -> 0
B21: Totals | C21: =C15+SUM(C17:C18) -> 9740263 | D21: =SUM(D10:D20) -> 0 | E21: =SUM(E10:E20) -> 0 | G21: =SUM(G10:G20) -> 9825000 | H21: =SUM(H10:H20) -> 0 | J21: =J14 -> 0 | L21: =SUM(L17:L20)+L15 -> 9740263 | M21: =SUM(M17:M18)+M15 -> 1
B23: SAFE Valuation Cap
B25: Post-Money Valuation Cap | E25: 50000000

Sheet Series A
B1: SIDEKICK (THINK MORE SECURITY, INC.)
B2: SERIES A ROUND
B3: Series A
C4: Common | D4: SAFE | G4: Option | I4: SAFE Conversion | L4: Option | N4: Series A | Q4: Option | S4: Total Capitalization
C5: # of | D5: $ | E5: SAFE | G5: Pool + | I5: $ | J5: Preferred | L5: Pool + | N5: $ | O5: Preferred | Q5: Pool + | S5: Total FD | T5: %
C6: Shares | D6: Invested | E6: Shares | G6: Pre-Funding | I6: Invested | J6: Shares | L6: Pre A | N6: Invested | O6: Shares | Q6: Post A | S6: Shares | T6: FD
B7: Common Stock and Options:
B8: Brian Hazzard | C8: ='Series Seed'!C10 -> 3600000 | S8: =C8+E8+G8+J8+L8+O8+Q8 -> 3600000 | T8: =S8/$S$21 -> 0.18689424
B9: David Wolpoff | C9: ='Series Seed'!C11 -> 3600000 | S9: =C9+E9+G9+J9+L9+O9+Q9 -> 3600000 | T9: =S9/$S$21 -> 0.18689424
B10: Other Common Shareholders | C10: ='Series Seed'!C12 -> 1429687 | S10: =C10+E10+G10+J10+L10+O10+Q10 -> 1429687 | T10: =S10/$S$21 -> 0.074222295
B11: ESOP Issued & Outstanding | C11: ='Series Seed'!C13 -> 1045471 | S11: =C11+E11+G11+J11+L11+O11+Q11 -> 1045471 | T11: =S11/$S$21 -> 0.054275696
B12: ESOP Available | C12: ='Series Seed'!C14 -> 65105 | S12: =C12+E12+G12+J12+L12+O12+Q12 -> 65105 | T12: =S12/$S$21 -> 0.0033799304
Q13: =IFERROR(ROUND(((O21+C21+E21+G21+J21+L21)/(1-C33))*C33-C12,0),0) -> 1867629 | S13: =C13+E13+G13+J13+L13+O13+Q13 -> 1867629 | T13: =S13/$S$21 -> 0.096958083
B14: Total Common | C14: =SUM(C8:C13) -> 9740263 | D14: =SUM(D8:D13) -> 0 | E14: =SUM(E8:E13) -> 0 | G14: =SUM(G8:G13) -> 0 | J14: =SUM(J8:J13) -> 0 | L14: =SUM(L8:L13) -> 0 | O14: =SUM(O8:O13) -> 0 | Q14: =SUM(Q8:Q13) -> 1867629 | S14: =SUM(S8:S13) -> 11607892 | T14: =S14/$S$21 -> 0.60262448
B15: Preferred Rounds
B16: Accomplice | D16: ='Series Seed'!G17 -> 8000000 | E16: =IFERROR(ROUND(D16/$E$23,0),0) -> 2311471 | N16: 5000000 | O16: =IFERROR(ROUND(N16/$O$23,0),0) -> 1203891 | S16: =E16+C16+J16+O16 -> 3515362 | T16: =S16/$S$21 -> 0.18250025
B17: 1011 Ventures | N17: 12000000 | O17: =IFERROR(ROUND(N17/$O$23,0),0) -> 2889338 | S17: =E17+C17+J17+O17 -> 2889338 | T17: =S17/$S$21 -> 0.15000017
B18: Other Series A Investors | N18: 3000000 | O18: =IFERROR(ROUND(N18/$O$23,0),0) -> 722335 | S18: =E18+C18+J18+O18 -> 722335 | T18: =S18/$S$21 -> 0.037500069
B19: Other SAFE Investors | D19: ='Series Seed'!G18 -> 1825000 | E19: =IFERROR(ROUND(D19/$E$23,0),0) -> 527304 | S19: =E19+C19+J19+O19 -> 527304 | T19: =S19/$S$21 -> 0.027375022
B21: Totals | C21: =C14+SUM(C16:C19) -> 9740263 | D21: =SUM(D8:D19) -> 9825000 | E21: =SUM(E8:E19) -> 2838775 | G21: =G13 -> 0 | I21: =SUM(I16:I20) -> 0 | J21: =SUM(J16:J20) -> 0 | L21: =L13 -> 0 | N21: =C30 -> 20000000 | O21: =SUM(O16:O20) -> 4815564 | Q21: =Q13 -> 1867629 | S21: =SUM(S16:S20)+S14 -> 19262231 | T21: =SUM(T16:T19)+T14 -> 1
B23: Price per Share | E23: =IFERROR(ROUND(50000000/(C21+E21+G21+Q13),4),0) -> 3.461 | O23: =IFERROR(ROUND(O24/(L21+J21+G21+E21+C21+Q13),4),0) -> 4.1532
B24: Pre-Money Valuation | O24: =O25-N21 -> 60000000
B25: Post-Money Valuation | E25: =50000000 -> 50000000 | O25: =C30/C31 -> 80000000
B27: Series A Assumptions:
B29: Pre-Money Valuation Step-up | C29: =O24/E25-1 -> 0.2
B30: Total Raised | C30: 20000000
B31: % Ownership | C31: 0.25
B32: 1011 Contribution | C32: 12000000
B33: Option Pool Expansion % | C33: 0.1
B34: SAFE Valuation Cap | C34: 50000000

Sheet Series B
B1: SIDEKICK (THINK MORE SECURITY, INC.)
B2: SERIES B ROUND
B3: Series B
C4: Common | D4: SAFE | G4: Option | I4: SAFE Conversion | L4: Option | N4: Series A | Q4: Option | S4: Series B | V4: Option | X4: Total Capitalization
C5: # of | D5: $ | E5: SAFE | G5: Pool + | I5: $ | J5: Preferred | L5: Pool + | N5: $ | O5: Preferred | Q5: Pool + | S5: $ | T5: Preferred | V5: Pool + | X5: Total FD | Y5: %
C6: Shares | D6: Invested | E6: Shares | G6: Pre-Funding | I6: Invested | J6: Shares | L6: Pre A | N6: Invested | O6: Shares | Q6: Pre B | S6: Invested | T6: Shares | V6: Post B | X6: Shares | Y6: FD
B7: Common Stock and Options:
B8: Brian Hazzard | C8: ='Series A'!C8 -> 3600000 | X8: =C8+E8+G8+J8+L8+O8+Q8+T8+V8 -> 3600000 | Y8: =X8/$X$22 -> 0.14266249
B9: David Wolpoff | C9: ='Series A'!C9 -> 3600000 | X9: =C9+E9+G9+J9+L9+O9+Q9+T9+V9 -> 3600000 | Y9: =X9/$X$22 -> 0.14266249
B10: Other Common Shareholders | C10: ='Series A'!C10 -> 1429687 | X10: =C10+E10+G10+J10+L10+O10+Q10+T10+V10 -> 1429687 | Y10: =X10/$X$22 -> 0.056656307
B11: ESOP Issued & Outstanding | C11: ='Series A'!C11 -> 1045471 | X11: =C11+E11+G11+J11+L11+O11+Q11+T11+V11 -> 1045471 | Y11: =X11/$X$22 -> 0.041430415
B12: ESOP Available | C12: ='Series A'!C12 -> 65105 | Q12: ='Series A'!Q13 -> 1867629 | X12: =C12+E12+G12+J12+L12+O12+Q12+T12+V12 -> 1932734 | Y12: =X12/$X$22 -> 0.076591289
V13: =IFERROR(ROUND(X22*C34,0),0) -> 1766407 | X13: =C13+E13+G13+J13+L13+O13+Q13+T13+V13 -> 1766407 | Y13: =X13/$X$22 -> 0.070000005
B14: Total Common | C14: =SUM(C8:C13) -> 9740263 | D14: =SUM(D8:D13) -> 0 | E14: =SUM(E8:E13) -> 0 | G14: =SUM(G8:G13) -> 0 | J14: =SUM(J8:J13) -> 0 | L14: =SUM(L8:L13) -> 0 | O14: =SUM(O8:O13) -> 0 | Q14: =SUM(Q8:Q13) -> 1867629 | T14: =SUM(T8:T13) -> 0 | V14: =SUM(V8:V13) -> 1766407 | X14: =SUM(X8:X13) -> 13374299 | Y14: =X14/$X$22 -> 0.53000299
B15: Preferred Rounds
B16: Accomplice | D16: ='Series A'!D16 -> 8000000 | E16: ='Series A'!E16 -> 2311471 | N16: ='Series A'!N16 -> 5000000 | O16: ='Series A'!O16 -> 1203891 | S16: =($S$22-$S$20)*(N16/$N$22) -> 3750000 | T16: =IFERROR(ROUND(S16/$T$24,0),0) -> 525718 | X16: =E16+C16+J16+O16+T16 -> 4041080 | Y16: =X16/$X$22 -> 0.16014181
B17: 1011 Ventures | N17: ='Series A'!N17 -> 12000000 | O17: ='Series A'!O17 -> 2889338 | S17: =($S$22-$S$20)*(N17/$N$22) -> 9000000 | T17: =IFERROR(ROUND(S17/$T$24,0),0) -> 1261724 | X17: =E17+C17+J17+O17+T17 -> 4151062 | Y17: =X17/$X$22 -> 0.16450023
B18: Other Series A Investors | N18: ='Series A'!N18 -> 3000000 | O18: ='Series A'!O18 -> 722335 | S18: =($S$22-$S$20)*(N18/$N$22) -> 2250000 | T18: =IFERROR(ROUND(S18/$T$24,0),0) -> 315431 | X18: =E18+C18+J18+O18+T18 -> 1037766 | Y18: =X18/$X$22 -> 0.041125078
B19: Other SAFE Investors | D19: ='Series A'!D19 -> 1825000 | E19: ='Series A'!E19 -> 527304 | X19: =E19+C19+J19+O19+T19 -> 527304 | Y19: =X19/$X$22 -> 0.02089625
B20: Other Series B Investors | S20: 15000000 | T20: =IFERROR(ROUND(S20/$T$24,0),0) -> 2102873 | X20: =E20+C20+J20+O20+T20 -> 2102873 | Y20: =X20/$X$22 -> 0.083333637
B22: Totals | C22: =C14+SUM(C16:C20) -> 9740263 | D22: =SUM(D8:D20) -> 9825000 | E22: =SUM(E8:E20) -> 2838775 | G22: =G13 -> 0 | I22: =SUM(I16:I21) -> 0 | J22: =SUM(J16:J21) -> 0 | L22: =L13 -> 0 | N22: =SUM(N16:N20) -> 20000000 | O22: =SUM(O16:O20) -> 4815564 | Q22: =Q12 -> 1867629 | S22: =C31 -> 30000000 | T22: =SUM(T16:T21) -> 4205746 | V22: =V13 -> 1766407 | X22: =SUM(X16:X21)+X14 -> 25234384 | Y22: =SUM(Y16:Y20)+Y14 -> 1
B24: Price per Share | E24: ='Series A'!E23 -> 3.461 | J24: ='Series A'!E23 -> 3.461 | O24: ='Series A'!O23 -> 4.1532 | T24: =IFERROR(ROUND(T25/(Q22+O22+L22+J22+G22+V13+E22+C22),4),0) -> 7.1331
B25: Pre-Money Valuation | E25: ='Series A'!E25 -> 50000000 | J25: ='Series A'!E25 -> 50000000 | O25: ='Series A'!O24 -> 60000000 | T25: =T26-S22 -> 150000000
B26: Post-Money Valuation | E26: ='Series A'!E25 -> 50000000 | J26: =J25+I22 -> 50000000 | O26: =O25+N22 -> 80000000 | T26: =C31/C32 -> 180000000
B28: Series B Assumptions:
B30: Pre-Money Valuation Step-up | C30: =T25/O26-1 -> 0.875
B31: Total Raised | C31: 30000000
B32: % Ownership | C32: 0.16666667
B33: % New Money | C33: =S20/S22 -> 0.5
B34: Option Pool Gross % | C34: 0.07
