Workbook

Sheet Sources and Uses
A1: Sources and Uses — Reed Industries
A3: Sources
A4: Term Loan B | B4: 250000000
A5: Mezzanine | B5: 50000000
A6: Sponsor Equity (plug) | B6: =B12-B4-B5 -> 210000000
A7: Total Sources | B7: =SUM(B4:B6) -> 510000000
A9: Uses
A10: Purchase price (EV) | B10: 500000000
A11: Transaction fees | B11: 10000000
A12: Total Uses | B12: =SUM(B10:B11) -> 510000000
A14: Check (Sources − Uses) | B14: =B7-B12 -> 0

Sheet Operating Model
A1: Operating Model — Reed Industries
B2: Y1 | C2: Y2 | D2: Y3 | E2: Y4 | F2: Y5
A3: Revenue | B3: =250000000*(1+0.06)^1 -> 265000000 | C3: =250000000*(1+0.06)^2 -> 280900000 | D3: =250000000*(1+0.06)^3 -> 297754000 | E3: =250000000*(1+0.06)^4 -> 315619240 | F3: =250000000*(1+0.06)^5 -> 3.3455639e+08
A4: EBITDA | B4: =50000000*(1+0.08)^1 -> 54000000 | C4: =50000000*(1+0.08)^2 -> 58320000 | D4: =50000000*(1+0.08)^3 -> 62985600 | E4: =50000000*(1+0.08)^4 -> 68024448 | F4: =50000000*(1+0.08)^5 -> 73466404
A5: D&A | B5: =12000000 -> 12000000 | C5: =12000000 -> 12000000 | D5: =12000000 -> 12000000 | E5: =12000000 -> 12000000 | F5: =12000000 -> 12000000
A6: EBIT | B6: =B4-B5 -> 42000000 | C6: =C4-C5 -> 46320000 | D6: =D4-D5 -> 50985600 | E6: =E4-E5 -> 56024448 | F6: =F4-F5 -> 61466404
A7: TLB beginning balance | B7: ='Sources and Uses'!B4 -> 250000000 | C7: =B17 -> 233975000 | D7: =C17 -> 2.1450469e+08 | E7: =D17 -> 1.9118714e+08 | F7: =E17 -> 1.635809e+08
A8: TLB interest | B8: =0.07*B7 -> 17500000 | C8: =0.07*C7 -> 16378250 | D8: =0.07*D7 -> 15015328 | E8: =0.07*E7 -> 13383100 | F8: =0.07*F7 -> 11450663
A9: Mezz interest | B9: =5000000 -> 5000000 | C9: =5000000 -> 5000000 | D9: =5000000 -> 5000000 | E9: =5000000 -> 5000000 | F9: =5000000 -> 5000000
A10: Pretax income | B10: =B6-B8-B9 -> 19500000 | C10: =C6-C8-C9 -> 24941750 | D10: =D6-D8-D9 -> 30970272 | E10: =E6-E8-E9 -> 37641348 | F10: =F6-F8-F9 -> 45015741
A11: Tax | B11: =MAX(0,B10)*0.25 -> 4875000 | C11: =MAX(0,C10)*0.25 -> 6235437.5 | D11: =MAX(0,D10)*0.25 -> 7742568 | E11: =MAX(0,E10)*0.25 -> 9410337 | F11: =MAX(0,F10)*0.25 -> 11253935
A12: Net income | B12: =B10-B11 -> 14625000 | C12: =C10-C11 -> 18706312 | D12: =D10-D11 -> 23227704 | E12: =E10-E11 -> 28231011 | F12: =F10-F11 -> 33761806
A13: Capex | B13: =0.04*B3 -> 10600000 | C13: =0.04*C3 -> 11236000 | D13: =0.04*D3 -> 11910160 | E13: =0.04*E3 -> 12624770 | F13: =0.04*F3 -> 13382256
A14: FCF | B14: =B12+B5-B13 -> 16025000 | C14: =C12+C5-C13 -> 19470312 | D14: =D12+D5-D13 -> 23317544 | E14: =E12+E5-E13 -> 27606241 | F14: =F12+F5-F13 -> 32379550
A15: Mandatory amort | B15: =2500000 -> 2500000 | C15: =2500000 -> 2500000 | D15: =2500000 -> 2500000 | E15: =2500000 -> 2500000 | F15: =2500000 -> 2500000
A16: Cash sweep | B16: =MAX(0,MIN(B14-B15,B7-B15)) -> 13525000 | C16: =MAX(0,MIN(C14-C15,C7-C15)) -> 16970312 | D16: =MAX(0,MIN(D14-D15,D7-D15)) -> 20817544 | E16: =MAX(0,MIN(E14-E15,E7-E15)) -> 25106241 | F16: =MAX(0,MIN(F14-F15,F7-F15)) -> 29879550
A17: TLB end balance | B17: =B7-B15-B16 -> 233975000 | C17: =C7-C15-C16 -> 2.1450469e+08 | D17: =D7-D15-D16 -> 1.9118714e+08 | E17: =E7-E15-E16 -> 1.635809e+08 | F17: =F7-F15-F16 -> 1.3120135e+08
A18: Mezz end balance | B18: =50000000 -> 50000000 | C18: =50000000 -> 50000000 | D18: =50000000 -> 50000000 | E18: =50000000 -> 50000000 | F18: =50000000 -> 50000000

Sheet Returns
A1: Returns — Reed Industries
A3: Exit multiple | B3: 11
A4: Hold period (years) | B4: 5
A6: Initial sponsor equity | B6: ='Sources and Uses'!B6 -> 210000000
A7: Exit Y5 EBITDA | B7: ='Operating Model'!F4 -> 73466404
A8: Exit EV | B8: =B3*B7 -> 8.0813044e+08
A9: TLB at exit | B9: ='Operating Model'!F17 -> 1.3120135e+08
A10: Mezz at exit | B10: ='Operating Model'!F18 -> 50000000
A11: Net debt at exit | B11: =B9+B10 -> 1.8120135e+08
A12: Exit equity value | B12: =B8-B11 -> 6.2692909e+08
A14: MOIC | B14: =B12/B6 -> 2.9853766
A15: IRR | B15: =(B12/B6)^(1/B4)-1 -> 0.24451411
