Workbook

Sheet __temp__

Sheet Detailed Cap Table
H2: Current
B3: Shareholder | C3: Founders CS | D3: RSA | E3: Options | F3: Exercised Options | G3: Total | H3: % FDS
B4: Brian Hazzard | C4: 3600000 | G4: =SUM(C4:F4) -> 3600000 | H4: =G4/$G$23 -> 0.36959988
B5: David Wolpoff | C5: 3600000 | G5: =SUM(C5:F5) -> 3600000 | H5: =G5/$G$23 -> 0.36959988
B6: Ian Lee | C6: 222187 | G6: =SUM(C6:F6) -> 222187 | H6: =G6/$G$23 -> 0.022811191
B7: Kyle Haugsness | C7: 592500 | G7: =SUM(C7:F7) -> 592500 | H7: =G7/$G$23 -> 0.06082998
B8: Paul Riegle | C8: 592500 | G8: =SUM(C8:F8) -> 592500 | H8: =G8/$G$23 -> 0.06082998
B9: Chris Butts | C9: 13500 | D9: 98900 | G9: =SUM(C9:F9) -> 112400 | H9: =G9/$G$23 -> 0.011539729
B10: Maurice Granfield | C10: 9000 | G10: =SUM(C10:F10) -> 9000 | H10: =G10/$G$23 -> 0.00092399969
B11: Pawan Lakshmanan | D11: 95000 | G11: =SUM(C11:F11) -> 95000 | H11: =G11/$G$23 -> 0.0097533301
B12: Matthew Howe | E12: 25000 | G12: =SUM(C12:F12) -> 25000 | H12: =G12/$G$23 -> 0.0025666658
B13: Andrew Ethan Boyce-Lewis | E13: 41562 | G13: =SUM(C13:F13) -> 41562 | H13: =G13/$G$23 -> 0.0042670306
B14: Eric McIntyre | D14: 285000 | G14: =SUM(C14:F14) -> 285000 | H14: =G14/$G$23 -> 0.02925999
B15: Patrick Heath | D15: 50000 | G15: =SUM(C15:F15) -> 50000 | H15: =G15/$G$23 -> 0.0051333316
B16: Chris Lord | D16: 285000 | G16: =SUM(C16:F16) -> 285000 | H16: =G16/$G$23 -> 0.02925999
B17: Eric Freedman | E17: 96186 | G17: =SUM(C17:F17) -> 96186 | H17: =G17/$G$23 -> 0.0098750927
B18: Miguel Bollar | E18: 48095 | G18: =SUM(C18:F18) -> 48095 | H18: =G18/$G$23 -> 0.0049377517
B19: Bradly Matheson | F19: 12395 | G19: =SUM(C19:F19) -> 12395 | H19: =G19/$G$23 -> 0.0012725529
B20: Cole Proctor | F20: 8333 | G20: =SUM(C20:F20) -> 8333 | H20: =G20/$G$23 -> 0.00085552105
B21: Available Options | D21: 65105 | G21: =SUM(C21:F21) -> 65105 | H21: =G21/$G$23 -> 0.0066841111
B23: Total | C23: =SUM(C4:C21) -> 8629687 | D23: =SUM(D4:D21) -> 879005 | E23: =SUM(E4:E21) -> 210843 | F23: =SUM(F4:F21) -> 20728 | G23: =SUM(G4:G21) -> 9740263

Sheet SAFE Investments
B3: Shareholder | C3: SAFE | E3: Notes
B4: Chris Butts | C4: 25000 | E4: IRA is actual investor
B5: Maurice Granfield | C5: 25000
B6: Accomplice Founder Fund, L.P. | C6: 137170.75
B7: Accomplice Fund IV, L.P | C7: 3846829.2
B8: Amir Bagherzadeh | C8: 16566 | E8: Transfer from Owl Rocl Capital II, LLC (Accomplice)
B9: Elizabeth A. Donaghey Irrevocable Trust 2016 | C9: 250000
B10: Gunderson Partners | C10: 100000
B11: Joe Arcadi | C11: 300000 | E11: IRA is actual investor
B12: Kamal Ravikant Capital, LP - E4 | C12: 37500 | E12: Navel
B13: Maria Cirino | C13: 250000
B14: Mike Viscuso | C14: 100000
B15: Mozart Holdings, LLC | C15: 41164 | E15: Transfer from Owl Rocl Capital II, LLC (Accomplice)
B16: Orcinus Generational Irrevocable Trust - 2024 | C16: 2328778 | E16: Transfer from Owl Rocl Capital II, LLC (Accomplice)
B17: Owl Rock Capital III, LLC | C17: 1506000 | E17: Accomplice
B18: Ralph Folz | C18: 50000
B19: Ravikant Capital, LP - F3 | C19: 212500 | E19: Navel
B20: Sean Leach | C20: 25000
B21: The Francis V. Castellucci Trust - 2020 | C21: 61746 | E21: Transfer from Owl Rocl Capital II, LLC (Accomplice)
B22: The Patrick M. Morley 1999 Trust, | C22: 100000
B23: Tom Barsi | C23: 100000
B24: Travis MacInnes | C24: 61746 | E24: Transfer from Owl Rocl Capital II, LLC (Accomplice)
B25: UWS West End Family Trust | C25: 250000 | E25: Mark Lotke
B27: Total | C27: =SUM(C4:C25) -> 9825000

Sheet Series A
B1: THINK MORE SECURITY & TEN ELEVEN SERIES A
B3: THINK MORE SECURITY & TEN ELEVEN SERIES A
C4: Common | D4: SAFE Preferred | G4: Series A | J4: Option | L4: Total Capitalization
C5: # of | D5: $ | E5: Preferred | G5: $ | H5: Preferred | J5: Pool + | L5: Total FD | M5: %
C6: Shares | D6: Invested | E6: Shares | G6: Invested | H6: Shares | J6: Pre A | L6: Shares | M6: FD
B7: Common Stock and Options:
B8: Brian Hazzard | C8: ='Detailed Cap Table'!G4 -> 3600000 | L8: =C8+E8+H8+J8 -> 3600000 | M8: =L8/$L$21 -> 0.19407512
B9: David Wolpoff | C9: ='Detailed Cap Table'!G5 -> 3600000 | L9: =C9+E9+H9+J9 -> 3600000 | M9: =L9/$L$21 -> 0.19407512
B10: Other Common Shareholders | C10: ='Detailed Cap Table'!G6+'Detailed Cap Table'!G7+'Detailed Cap Table'!G8+'Detailed Cap Table'!G9+'Detailed Cap Table'!G10+'Detailed Cap Table'!G11+'Detailed Cap Table'!G14+'Detailed Cap Table'!G15+'Detailed Cap Table'!G16 -> 2243587 | L10: =C10+E10+H10+J10 -> 2243587 | M10: =L10/$L$21 -> 0.12095123
B11: ESOP Issued & Outstanding | C11: ='Detailed Cap Table'!G12+'Detailed Cap Table'!G13+'Detailed Cap Table'!G17+'Detailed Cap Table'!G18+'Detailed Cap Table'!G19+'Detailed Cap Table'!G20 -> 231571 | L11: =C11+E11+H11+J11 -> 231571 | M11: =L11/$L$21 -> 0.012483936
B12: ESOP Available | C12: ='Detailed Cap Table'!G21 -> 65105 | J12: =IFERROR(ROUND($C$34*$L$21-C12,0),0) -> 1789847 | L12: =C12+E12+H12+J12 -> 1854952 | M12: =L12/$L$21 -> 0.10000001
B14: Total Common | C14: =SUM(C8:C13) -> 9740263 | E14: =SUM(E8:E13) -> 0 | H14: =SUM(H8:H13) -> 0 | J14: =SUM(J8:J13) -> 1789847 | L14: =SUM(L8:L13) -> 11530110 | M14: =L14/$L$21 -> 0.62158542
B15: Preferred Rounds
B16: Accomplice | D16: ='SAFE Investments'!C6+'SAFE Investments'!C7+'SAFE Investments'!C8+'SAFE Investments'!C15+'SAFE Investments'!C16+'SAFE Investments'!C17+'SAFE Investments'!C21+'SAFE Investments'!C24 -> 8000000 | E16: =IFERROR(ROUND(D16/$E$23,0),0) -> 1939582 | G16: 5000000 | H16: =IFERROR(ROUND(G16/$H$23,0),0) -> 1159340 | L16: =C16+E16+H16+J16 -> 3098922 | M16: =L16/$L$21 -> 0.16706213
B17: Other SAFE Investors | D17: ='SAFE Investments'!C4+'SAFE Investments'!C5+'SAFE Investments'!C9+'SAFE Investments'!C10+'SAFE Investments'!C11+'SAFE Investments'!C12+'SAFE Investments'!C13+'SAFE Investments'!C14+'SAFE Investments'!C18+'SAFE Investments'!C19+'SAFE Investments'!C20+'SAFE Investments'!C22+'SAFE Investments'!C23+'SAFE Investments'!C25 -> 1825000 | E17: =IFERROR(ROUND(D17/$E$23,0),0) -> 442467 | L17: =C17+E17+H17+J17 -> 442467 | M17: =L17/$L$21 -> 0.023853288
B18: 1011 | G18: 12000000 | H18: =IFERROR(ROUND(G18/$H$23,0),0) -> 2782415 | L18: =C18+E18+H18+J18 -> 2782415 | M18: =L18/$L$21 -> 0.14999932
B19: Other Series A Investors | G19: 3000000 | H19: =IFERROR(ROUND(G19/$H$23,0),0) -> 695604 | L19: =C19+E19+H19+J19 -> 695604 | M19: =L19/$L$21 -> 0.037499842
B21: Totals | C21: =C14+SUM(C16:C19) -> 9740263 | D21: =SUM(D16:D20) -> 9825000 | E21: =SUM(E16:E20) -> 2382049 | G21: =SUM(G16:G20) -> 20000000 | H21: =SUM(H16:H20) -> 4637359 | J21: =J12 -> 1789847 | L21: =SUM(L16:L20)+L14 -> 18549518 | M21: =SUM(M16:M19)+M14 -> 1
B23: Price per Share | E23: =IFERROR(ROUND(($C$35-D21)/'Detailed Cap Table'!G23, 4), 0) -> 4.1246 | H23: =IFERROR(ROUND(H24/(L21-H21), 4), 0) -> 4.3128
B24: Pre-Money Valuation | H24: =H25-G21 -> 60000000
B25: Post-Money Valuation | H25: =C29+C30 -> 80000000
B27: Series A Assumptions:
B29: Pre-Money Valuation | C29: 60000000
B30: Total Raised | C30: 20000000
B31: 1011 Investment | C31: 12000000
B32: Accomplice Investment | C32: 5000000
B33: Other Series A Investment | C33: 3000000
B34: Option Pool Target | C34: 0.1
B35: SAFE Post-Money Cap | C35: 50000000
B36: Existing Unallocated Options | C36: ='Detailed Cap Table'!G21 -> 65105

Sheet Series B
B1: THINK MORE SECURITY & TEN ELEVEN SERIES B
B3: THINK MORE SECURITY & TEN ELEVEN SERIES B
C4: Common | D4: SAFE Preferred | G4: Series A | J4: Option | L4: Series B | O4: Option | Q4: Total Capitalization
C5: # of | D5: $ | E5: Preferred | G5: $ | H5: Preferred | J5: Pool + | L5: $ | M5: Preferred | O5: Pool + | Q5: Total FD | R5: %
C6: Shares | D6: Invested | E6: Shares | G6: Invested | H6: Shares | J6: Pre A | L6: Invested | M6: Shares | O6: Pre B | Q6: Shares | R6: FD
B7: Common Stock and Options:
B8: Brian Hazzard | C8: ='Series A'!C8 -> 3600000 | Q8: =C8+E8+H8+J8+M8+O8 -> 3600000 | R8: =Q8/$Q$21 -> 0.148144
B9: David Wolpoff | C9: ='Series A'!C9 -> 3600000 | Q9: =C9+E9+H9+J9+M9+O9 -> 3600000 | R9: =Q9/$Q$21 -> 0.148144
B10: Other Common Shareholders | C10: ='Series A'!C10 -> 2243587 | Q10: =C10+E10+H10+J10+M10+O10 -> 2243587 | R10: =Q10/$Q$21 -> 0.0923261
B11: ESOP Issued & Outstanding | C11: ='Series A'!C11 -> 231571 | Q11: =C11+E11+H11+J11+M11+O11 -> 231571 | R11: =Q11/$Q$21 -> 0.0095294041
B12: ESOP Available | C12: ='Series A'!C12 -> 65105 | J12: ='Series A'!J12 -> 1789847 | O12: =IFERROR(ROUND($C$34*$Q$21,0),0) -> 1701048 | Q12: =C12+E12+H12+J12+M12+O12 -> 3556000 | R12: =Q12/$Q$21 -> 0.14633335
B14: Total Common | C14: =SUM(C8:C13) -> 9740263 | E14: =SUM(E8:E13) -> 0 | H14: =SUM(H8:H13) -> 0 | J14: =SUM(J8:J13) -> 1789847 | M14: =SUM(M8:M13) -> 0 | O14: =SUM(O8:O13) -> 1701048 | Q14: =SUM(Q8:Q13) -> 13231158 | R14: =Q14/$Q$21 -> 0.54447686
B15: Preferred Rounds
B16: Accomplice | D16: ='Series A'!D16 -> 8000000 | E16: ='Series A'!E16 -> 1939582 | G16: ='Series A'!G16 -> 5000000 | H16: ='Series A'!H16 -> 1159340 | L16: =C38*C32 -> 3750000 | M16: =IFERROR(ROUND(L16/$M$23,0),0) -> 506264 | Q16: =C16+E16+H16+J16+M16+O16 -> 3605186 | R16: =Q16/$Q$21 -> 0.14835741
B17: Other SAFE Investors | D17: ='Series A'!D17 -> 1825000 | E17: ='Series A'!E17 -> 442467 | Q17: =C17+E17+H17+J17+M17+O17 -> 442467 | R17: =Q17/$Q$21 -> 0.018208009
B18: 1011 | G18: ='Series A'!G18 -> 12000000 | H18: ='Series A'!H18 -> 2782415 | L18: =C37*C32 -> 9000000 | M18: =IFERROR(ROUND(L18/$M$23,0),0) -> 1215034 | Q18: =C18+E18+H18+J18+M18+O18 -> 3997449 | R18: =Q18/$Q$21 -> 0.16449947
B19: Other Series A Investors | G19: ='Series A'!G19 -> 3000000 | H19: ='Series A'!H19 -> 695604 | L19: =C39*C32 -> 2250000 | M19: =IFERROR(ROUND(L19/$M$23,0),0) -> 303759 | Q19: =C19+E19+H19+J19+M19+O19 -> 999363 | R19: =Q19/$Q$21 -> 0.041124899
B20: Other Series B Investors | L20: 15000000 | M20: =IFERROR(ROUND(L20/$M$23,0),0) -> 2025057 | Q20: =C20+E20+H20+J20+M20+O20 -> 2025057 | R20: =Q20/$Q$21 -> 0.083333347
B21: Totals | C21: =C14+SUM(C16:C20) -> 9740263 | D21: =SUM(D16:D20) -> 9825000 | E21: =SUM(E16:E20) -> 2382049 | G21: =SUM(G16:G20) -> 20000000 | H21: =SUM(H16:H20) -> 4637359 | J21: =J12 -> 1789847 | L21: =SUM(L16:L20) -> 30000000 | M21: =SUM(M16:M20) -> 4050114 | O21: =O12 -> 1701048 | Q21: =SUM(Q16:Q20)+Q14 -> 24300680 | R21: =SUM(R16:R20)+R14 -> 1
B23: Price per Share | E23: ='Series A'!E23 -> 4.1246 | H23: ='Series A'!H23 -> 4.3128 | M23: =IFERROR(ROUND(M24/(Q21-M21), 4), 0) -> 7.4072
B24: Pre-Money Valuation | M24: =M25-L21 -> 150000000
B25: Post-Money Valuation | M25: =C29+C30 -> 180000000
B27: Series B Assumptions:
B29: Pre-Money Valuation | C29: 150000000
B30: Total Raised | C30: 30000000
B31: Other Series B Investors | C31: 15000000
B32: Pro Rata Pool (remaining) | C32: =C30-C31 -> 15000000
B33: Pro Rata Basis | C33: Series A new money
B34: Option Pool Gross Top-up Target | C34: 0.07
B36: Pro Rata Splits:
B37: 1011 % of pro rata | C37: ='Series A'!G18/'Series A'!G21 -> 0.6
B38: Accomplice % of pro rata | C38: ='Series A'!G16/'Series A'!G21 -> 0.25
B39: Other Series A % of pro rata | C39: ='Series A'!G19/'Series A'!G21 -> 0.15
