Workbook

Sheet __temp__

Sheet Detailed Cap Table
H2: Current
B3: Shareholder | C3: Founders CS | D3: RSA | E3: Options | F3: Exercised Options | G3: Total | H3: % FDS
B4: Brian Hazzard | C4: 3600000 | G4: =SUM(C4:F4) -> 3600000 | H4: =G4/$G$23 -> 0.36959988
B5: David Wolpoff | C5: 3600000 | G5: =SUM(C5:F5) -> 3600000 | H5: =G5/$G$23 -> 0.36959988
B6: Ian Lee | C6: 222187 | G6: =SUM(C6:F6) -> 222187 | H6: =G6/$G$23 -> 0.022811191
B7: Kyle Haugsness | C7: 592500 | G7: =SUM(C7:F7) -> 592500 | H7: =G7/$G$23 -> 0.06082998
B8: Paul Riegle | C8: 592500 | G8: =SUM(C8:F8) -> 592500 | H8: =G8/$G$23 -> 0.06082998
B9: Chris Butts | C9: 13500 | D9: 98900 | G9: =SUM(C9:F9) -> 112400 | H9: =G9/$G$23 -> 0.011539729
B10: Maurice Granfield | C10: 9000 | G10: =SUM(C10:F10) -> 9000 | H10: =G10/$G$23 -> 0.00092399969
B11: Pawan Lakshmanan | D11: 95000 | G11: =SUM(C11:F11) -> 95000 | H11: =G11/$G$23 -> 0.0097533301
B12: Matthew Howe | E12: 25000 | G12: =SUM(C12:F12) -> 25000 | H12: =G12/$G$23 -> 0.0025666658
B13: Andrew Ethan Boyce-Lewis | E13: 41562 | G13: =SUM(C13:F13) -> 41562 | H13: =G13/$G$23 -> 0.0042670306
B14: Eric McIntyre | D14: 285000 | G14: =SUM(C14:F14) -> 285000 | H14: =G14/$G$23 -> 0.02925999
B15: Patrick Heath | D15: 50000 | G15: =SUM(C15:F15) -> 50000 | H15: =G15/$G$23 -> 0.0051333316
B16: Chris Lord | D16: 285000 | G16: =SUM(C16:F16) -> 285000 | H16: =G16/$G$23 -> 0.02925999
B17: Eric Freedman | E17: 96186 | G17: =SUM(C17:F17) -> 96186 | H17: =G17/$G$23 -> 0.0098750927
B18: Miguel Bollar | E18: 48095 | G18: =SUM(C18:F18) -> 48095 | H18: =G18/$G$23 -> 0.0049377517
B19: Bradly Matheson | F19: 12395 | G19: =SUM(C19:F19) -> 12395 | H19: =G19/$G$23 -> 0.0012725529
B20: Cole Proctor | F20: 8333 | G20: =SUM(C20:F20) -> 8333 | H20: =G20/$G$23 -> 0.00085552105
B21: Available Options | D21: 65105 | G21: =SUM(C21:F21) -> 65105 | H21: =G21/$G$23 -> 0.0066841111
B23: Total | C23: =SUM(C4:C21) -> 8629687 | D23: =SUM(D4:D21) -> 879005 | E23: =SUM(E4:E21) -> 210843 | F23: =SUM(F4:F21) -> 20728 | G23: =SUM(G4:G21) -> 9740263

Sheet SAFE Investments
B3: Shareholder | C3: SAFE | E3: Notes
B4: Chris Butts | C4: 25000 | E4: IRA is actual investor
B5: Maurice Granfield | C5: 25000
B6: Accomplice Founder Fund, L.P. | C6: 137170.75
B7: Accomplice Fund IV, L.P | C7: 3846829.2
B8: Amir Bagherzadeh | C8: 16566 | E8: Transfer from Owl Rocl Capital II, LLC (Accomplice)
B9: Elizabeth A. Donaghey Irrevocable Trust 2016 | C9: 250000
B10: Gunderson Partners | C10: 100000
B11: Joe Arcadi | C11: 300000 | E11: IRA is actual investor
B12: Kamal Ravikant Capital, LP - E4 | C12: 37500 | E12: Navel
B13: Maria Cirino | C13: 250000
B14: Mike Viscuso | C14: 100000
B15: Mozart Holdings, LLC | C15: 41164 | E15: Transfer from Owl Rocl Capital II, LLC (Accomplice)
B16: Orcinus Generational Irrevocable Trust - 2024 | C16: 2328778 | E16: Transfer from Owl Rocl Capital II, LLC (Accomplice)
B17: Owl Rock Capital III, LLC | C17: 1506000 | E17: Accomplice
B18: Ralph Folz | C18: 50000
B19: Ravikant Capital, LP - F3 | C19: 212500 | E19: Navel
B20: Sean Leach | C20: 25000
B21: The Francis V. Castellucci Trust - 2020 | C21: 61746 | E21: Transfer from Owl Rocl Capital II, LLC (Accomplice)
B22: The Patrick M. Morley 1999 Trust, | C22: 100000
B23: Tom Barsi | C23: 100000
B24: Travis MacInnes | C24: 61746 | E24: Transfer from Owl Rocl Capital II, LLC (Accomplice)
B25: UWS West End Family Trust | C25: 250000 | E25: Mark Lotke
B27: Total | C27: =SUM(C4:C25) -> 9825000

Sheet SeriesA
B4: SIDEKICK (THINK MORE SECURITY) & TEN ELEVEN (1011)
B5: SERIES A
C6: Common | D6: SAFE | G6: Series A | J6: Option | L6: Total Capitalization
C7: # of | D7: $ | E7: Preferred | G7: $ | H7: Preferred | J7: Pool + | L7: Total FD | M7: %
C8: Shares | D8: Invested | E8: Shares | G8: Invested | H8: Shares | J8: Pre A | L8: Shares | M8: FD
B9: Common Stock and Options:
B10: Brian Hazzard | C10: ='Detailed Cap Table'!G4 -> 3600000 | L10: =C10+E10+H10+J10 -> 3600000 | M10: =L10/$L$22 -> 0.19407509
B11: David Wolpoff | C11: ='Detailed Cap Table'!G5 -> 3600000 | L11: =C11+E11+H11+J11 -> 3600000 | M11: =L11/$L$22 -> 0.19407509
B12: Other Common | C12: ='Detailed Cap Table'!C23-'Detailed Cap Table'!C4-'Detailed Cap Table'!C5+'Detailed Cap Table'!D23-'Detailed Cap Table'!D21+'Detailed Cap Table'!F23 -> 2264315 | L12: =C12+E12+H12+J12 -> 2264315 | M12: =L12/$L$22 -> 0.12206865
B13: ESOP Issued & Outstanding | C13: ='Detailed Cap Table'!E23 -> 210843 | L13: =C13+E13+H13+J13 -> 210843 | M13: =L13/$L$22 -> 0.011366493
B14: ESOP Available | C14: ='Detailed Cap Table'!G21 -> 65105 | J14: =IFERROR(ROUND(0.1*L22-C14,0),0) -> 1789847 | L14: =C14+E14+H14+J14 -> 1854952 | M14: =L14/$L$22 -> 0.099999995
B15: Total Common | C15: =SUM(C10:C14) -> 9740263 | D15: =SUM(D10:D14) -> 0 | E15: =SUM(E10:E14) -> 0 | G15: =SUM(G10:G14) -> 0 | H15: =SUM(H10:H14) -> 0 | J15: =SUM(J10:J14) -> 1789847 | L15: =SUM(L10:L14) -> 11530110 | M15: =L15/$L$22 -> 0.62158532
B16: Preferred Rounds
B17: Accomplice | D17: ='SAFE Investments'!C6+'SAFE Investments'!C7+'SAFE Investments'!C8+'SAFE Investments'!C15+'SAFE Investments'!C16+'SAFE Investments'!C17+'SAFE Investments'!C21+'SAFE Investments'!C24 -> 8000000 | E17: =IFERROR(ROUND(D17/$E$24,0),0) -> 1939567 | G17: 5000000 | H17: =IFERROR(ROUND(G17/$H$24,0),0) -> 1159345 | L17: =C17+E17+H17+J17 -> 3098912 | M17: =L17/$L$22 -> 0.16706156
B18: Other Investors | D18: ='SAFE Investments'!C27-D17 -> 1825000 | E18: =IFERROR(ROUND(D18/$E$24,0),0) -> 442464 | L18: =C18+E18+H18+J18 -> 442464 | M18: =L18/$L$22 -> 0.023853123
B19: Ten Eleven Ventures (1011) | G19: 12000000 | H19: =IFERROR(ROUND(G19/$H$24,0),0) -> 2782428 | L19: =C19+E19+H19+J19 -> 2782428 | M19: =L19/$L$22 -> 0.14999999
B20: Other Series A | G20: 3000000 | H20: =IFERROR(ROUND(G20/$H$24,0),0) -> 695607 | L20: =C20+E20+H20+J20 -> 695607 | M20: =L20/$L$22 -> 0.037499998
B22: Totals | C22: =C15+SUM(C17:C20) -> 9740263 | D22: =SUM(D10:D20) -> 9825000 | E22: =SUM(E10:E20) -> 2382031 | G22: =SUM(G10:G20) -> 20000000 | H22: =SUM(H10:H20) -> 4637380 | J22: =J14 -> 1789847 | L22: =SUM(L17:L20)+L15 -> 18549521 | M22: =SUM(M17:M20)+M15 -> 1
B24: Price per Share | E24: =(50000000-'SAFE Investments'!C27)/'Detailed Cap Table'!G23 -> 4.124632 | H24: =H26/L22 -> 4.3127798
B25: Pre-Money Valuation | E25: =E26-D22 -> 40175000 | H25: =H26-G22 -> 60000000
B26: Post-Money Valuation | E26: 50000000 | H26: 80000000

Sheet SeriesB
B1: SIDEKICK (THINK MORE SECURITY) & TEN ELEVEN (1011)
B2: SERIES B
C4: Common | D4: SAFE | G4: Option | I4: Series A | L4: Option | N4: Series B | Q4: Option | S4: Total Capitalization
C5: # of | D5: $ | E5: Preferred | G5: Pool + | I5: $ | J5: Preferred | L5: Pool + | N5: $ | O5: Preferred | Q5: Pool + | S5: Total FD | T5: %
B6: (see SeriesA) | C6: Shares | D6: Invested | E6: Shares | G6: Pre A | I6: Invested | J6: Shares | L6: Pre B | N6: Invested | O6: Shares | Q6: Post B | S6: Shares | T6: FD
B7: Common Stock and Options:
B8: Brian Hazzard | C8: =SeriesA!C10 -> 3600000 | S8: =C8+E8+G8+J8+L8+O8+Q8 -> 3600000 | T8: =S8/$S$21 -> 0.14814398
B9: David Wolpoff | C9: =SeriesA!C11 -> 3600000 | S9: =C9+E9+G9+J9+L9+O9+Q9 -> 3600000 | T9: =S9/$S$21 -> 0.14814398
B10: Other Common | C10: =SeriesA!C12 -> 2264315 | S10: =C10+E10+G10+J10+L10+O10+Q10 -> 2264315 | T10: =S10/$S$21 -> 0.093179068
B11: ESOP Issued & Outstanding | C11: =SeriesA!C13 -> 210843 | S11: =C11+E11+G11+J11+L11+O11+Q11 -> 210843 | T11: =S11/$S$21 -> 0.0086764228
B12: ESOP Available | C12: =SeriesA!C14 -> 65105 | G12: =SeriesA!J14 -> 1789847 | Q12: =IFERROR(ROUND(0.07*S21,0),0) -> 1701048 | S12: =C12+E12+G12+J12+L12+O12+Q12 -> 3556000 | T12: =S12/$S$21 -> 0.14633334
V13: =Q12/S21 -> 0.070000008
B14: Total Common | C14: =SUM(C8:C12) -> 9740263 | D14: =SUM(D8:D12) -> 0 | E14: =SUM(E8:E12) -> 0 | G14: =SUM(G8:G12) -> 1789847 | I14: =SUM(I8:I12) -> 0 | J14: =SUM(J8:J12) -> 0 | L14: =SUM(L8:L12) -> 0 | N14: =SUM(N8:N12) -> 0 | O14: =SUM(O8:O12) -> 0 | Q14: =SUM(Q8:Q12) -> 1701048 | S14: =SUM(S8:S12) -> 13231158 | T14: =S14/$S$21 -> 0.5444768
B15: Preferred Rounds
B16: Accomplice | D16: =SeriesA!D17 -> 8000000 | E16: =SeriesA!E17 -> 1939567 | I16: =SeriesA!G17 -> 5000000 | J16: =SeriesA!H17 -> 1159345 | N16: 3750000 | O16: =IFERROR(ROUND(N16/$O$23,0),0) -> 506264 | S16: =E16+C16+J16+O16 -> 3605176 | T16: =S16/$S$21 -> 0.14835698
B17: Other Investors | D17: =SeriesA!D18 -> 1825000 | E17: =SeriesA!E18 -> 442464 | S17: =E17+C17+J17+O17 -> 442464 | T17: =S17/$S$21 -> 0.018207883
B18: Ten Eleven Ventures (1011) | I18: =SeriesA!G19 -> 12000000 | J18: =SeriesA!H19 -> 2782428 | N18: 9000000 | O18: =IFERROR(ROUND(N18/$O$23,0),0) -> 1215034 | S18: =E18+C18+J18+O18 -> 3997462 | T18: =S18/$S$21 -> 0.16449999
B19: Other Series A | I19: =SeriesA!G20 -> 3000000 | J19: =SeriesA!H20 -> 695607 | N19: 2250000 | O19: =IFERROR(ROUND(N19/$O$23,0),0) -> 303759 | S19: =E19+C19+J19+O19 -> 999366 | T19: =S19/$S$21 -> 0.041125017
B20: Other Series B | N20: 15000000 | O20: =IFERROR(ROUND(N20/$O$23,0),0) -> 2025057 | S20: =E20+C20+J20+O20 -> 2025057 | T20: =S20/$S$21 -> 0.083333337
B21: Totals | C21: =C14+SUM(C16:C20) -> 9740263 | D21: =SUM(D8:D20) -> 9825000 | E21: =SUM(E8:E20) -> 2382031 | G21: =G12 -> 1789847 | I21: =SUM(I16:I20) -> 20000000 | J21: =SUM(J16:J20) -> 4637380 | L21: =L12 -> 0 | N21: =SUM(N16:N20) -> 30000000 | O21: =SUM(O16:O20) -> 4050114 | Q21: =Q12 -> 1701048 | S21: =SUM(S16:S20)+S14 -> 24300683 | T21: =SUM(T16:T20)+T14 -> 1
B23: Price per Share | E23: =SeriesA!E24 -> 4.124632 | J23: =SeriesA!H24 -> 4.3127798 | O23: =O25/S21 -> 7.4071992
B24: Pre-Money Valuation | E24: =SeriesA!E25 -> 40175000 | J24: =SeriesA!H25 -> 60000000 | O24: =O25-N21 -> 150000000
B25: Post-Money Valuation | E25: =SeriesA!E26 -> 50000000 | J25: =SeriesA!H26 -> 80000000 | O25: 180000000
B27: Series B Assumptions:
B29: Pre-Money Valuation Step-up | C29: =O24/J25-1 -> 0.875
B30: Total Raised | C30: 30000000
B31: % Ownership | C31: =C30/O25 -> 0.16666667
